TGPred/TGPred.py
TGPred/__init__.py
TGPred-0.1.0.dist-info/LICENSE
TGPred-0.1.0.dist-info/METADATA
TGPred-0.1.0.dist-info/WHEEL
TGPred-0.1.0.dist-info/top_level.txt
TGPred-0.1.0.dist-info/RECORD
