Metadata-Version: 2.1
Name: TGPred
Version: 0.1.0
Summary: TGPred: Efficient methods for predicting target genes of a transcription factor by integrating statistics, machine learning, and optimization.
Home-page: https://github.com/tobefuture/TGPred
Author: Ling Zhang
Author-email: lingzhan@mtu.edu
License: UNKNOWN
Platform: UNKNOWN
Classifier: Programming Language :: Python :: 3
Classifier: License :: OSI Approved :: MIT License
Classifier: Operating System :: OS Independent
Requires-Python: >=3.6
License-File: LICENSE
Requires-Dist: numpy
Requires-Dist: pandas
Requires-Dist: cvxpy
Requires-Dist: networkx
Requires-Dist: sklearn
